<annotation>
	<folder>group1</folder>
	<filename>FILE200420-194459F_864.jpg</filename>
	<path>F:\Night-time_data\Changchun_Snow_20200420\Changchun_grp1\Changchun_grp1\group1\FILE200420-194459F_864.jpg</path>
	<source>
		<database>Unknown</database>
	</source>
	<size>
		<width>1920</width>
		<height>1080</height>
		<depth>3</depth>
	</size>
	<segmented>0</segmented>
	<object>
		<name>person</name>
		<pose>Unspecified</pose>
		<truncated>0</truncated>
		<difficult>0</difficult>
		<bndbox>
			<xmin>1105</xmin>
			<ymin>642</ymin>
			<xmax>1131</xmax>
			<ymax>730</ymax>
		</bndbox>
	</object>
	<object>
		<name>person</name>
		<pose>Unspecified</pose>
		<truncated>0</truncated>
		<difficult>0</difficult>
		<bndbox>
			<xmin>961</xmin>
			<ymin>668</ymin>
			<xmax>993</xmax>
			<ymax>706</ymax>
		</bndbox>
	</object>
	<object>
		<name>minibus</name>
		<pose>Unspecified</pose>
		<truncated>0</truncated>
		<difficult>0</difficult>
		<bndbox>
			<xmin>1681</xmin>
			<ymin>509</ymin>
			<xmax>1843</xmax>
			<ymax>703</ymax>
		</bndbox>
	</object>
	<object>
		<name>minibus</name>
		<pose>Unspecified</pose>
		<truncated>0</truncated>
		<difficult>0</difficult>
		<bndbox>
			<xmin>1347</xmin>
			<ymin>604</ymin>
			<xmax>1474</xmax>
			<ymax>693</ymax>
		</bndbox>
	</object>
	<object>
		<name>person</name>
		<pose>Unspecified</pose>
		<truncated>0</truncated>
		<difficult>0</difficult>
		<bndbox>
			<xmin>1186</xmin>
			<ymin>642</ymin>
			<xmax>1216</xmax>
			<ymax>714</ymax>
		</bndbox>
	</object>
	<object>
		<name>vehicle</name>
		<pose>Unspecified</pose>
		<truncated>0</truncated>
		<difficult>0</difficult>
		<bndbox>
			<xmin>1242</xmin>
			<ymin>643</ymin>
			<xmax>1317</xmax>
			<ymax>698</ymax>
		</bndbox>
	</object>
</annotation>
