<annotation>
	<folder>group1</folder>
	<filename>FILE200420-194700F_96.jpg</filename>
	<path>F:\Night-time_data\Changchun_Snow_20200420\Changchun_grp1\Changchun_grp1\group1\FILE200420-194700F_96.jpg</path>
	<source>
		<database>Unknown</database>
	</source>
	<size>
		<width>1920</width>
		<height>1080</height>
		<depth>3</depth>
	</size>
	<segmented>0</segmented>
	<object>
		<name>vehicle</name>
		<pose>Unspecified</pose>
		<truncated>0</truncated>
		<difficult>0</difficult>
		<bndbox>
			<xmin>1246</xmin>
			<ymin>664</ymin>
			<xmax>1300</xmax>
			<ymax>702</ymax>
		</bndbox>
	</object>
	<object>
		<name>vehicle</name>
		<pose>Unspecified</pose>
		<truncated>0</truncated>
		<difficult>0</difficult>
		<bndbox>
			<xmin>807</xmin>
			<ymin>674</ymin>
			<xmax>855</xmax>
			<ymax>705</ymax>
		</bndbox>
	</object>
	<object>
		<name>traffic_sign</name>
		<pose>Unspecified</pose>
		<truncated>0</truncated>
		<difficult>0</difficult>
		<bndbox>
			<xmin>1243</xmin>
			<ymin>315</ymin>
			<xmax>1315</xmax>
			<ymax>402</ymax>
		</bndbox>
	</object>
	<object>
		<name>vehicle</name>
		<pose>Unspecified</pose>
		<truncated>0</truncated>
		<difficult>0</difficult>
		<bndbox>
			<xmin>995</xmin>
			<ymin>664</ymin>
			<xmax>1021</xmax>
			<ymax>684</ymax>
		</bndbox>
	</object>
	<object>
		<name>vehicle</name>
		<pose>Unspecified</pose>
		<truncated>0</truncated>
		<difficult>0</difficult>
		<bndbox>
			<xmin>922</xmin>
			<ymin>672</ymin>
			<xmax>952</xmax>
			<ymax>691</ymax>
		</bndbox>
	</object>
	<object>
		<name>vehicle</name>
		<pose>Unspecified</pose>
		<truncated>0</truncated>
		<difficult>0</difficult>
		<bndbox>
			<xmin>877</xmin>
			<ymin>671</ymin>
			<xmax>905</xmax>
			<ymax>690</ymax>
		</bndbox>
	</object>
	<object>
		<name>vehicle</name>
		<pose>Unspecified</pose>
		<truncated>0</truncated>
		<difficult>0</difficult>
		<bndbox>
			<xmin>192</xmin>
			<ymin>677</ymin>
			<xmax>387</xmax>
			<ymax>758</ymax>
		</bndbox>
	</object>
	<object>
		<name>vehicle</name>
		<pose>Unspecified</pose>
		<truncated>0</truncated>
		<difficult>0</difficult>
		<bndbox>
			<xmin>1155</xmin>
			<ymin>670</ymin>
			<xmax>1188</xmax>
			<ymax>695</ymax>
		</bndbox>
	</object>
</annotation>
