<annotation>
	<folder>group1</folder>
	<filename>FILE200420-174457F_744.jpg</filename>
	<path>F:\Night-time_data\Changchun_Snow_20200420\Changchun_grp1\Changchun_grp1\group1\FILE200420-174457F_744.jpg</path>
	<source>
		<database>Unknown</database>
	</source>
	<size>
		<width>1920</width>
		<height>1080</height>
		<depth>3</depth>
	</size>
	<segmented>0</segmented>
	<object>
		<name>vehicle</name>
		<pose>Unspecified</pose>
		<truncated>0</truncated>
		<difficult>0</difficult>
		<bndbox>
			<xmin>1064</xmin>
			<ymin>664</ymin>
			<xmax>1158</xmax>
			<ymax>732</ymax>
		</bndbox>
	</object>
	<object>
		<name>traffic_sign</name>
		<pose>Unspecified</pose>
		<truncated>0</truncated>
		<difficult>0</difficult>
		<bndbox>
			<xmin>1136</xmin>
			<ymin>340</ymin>
			<xmax>1328</xmax>
			<ymax>428</ymax>
		</bndbox>
	</object>
	<object>
		<name>vehicle</name>
		<pose>Unspecified</pose>
		<truncated>0</truncated>
		<difficult>0</difficult>
		<bndbox>
			<xmin>372</xmin>
			<ymin>654</ymin>
			<xmax>538</xmax>
			<ymax>742</ymax>
		</bndbox>
	</object>
	<object>
		<name>vehicle</name>
		<pose>Unspecified</pose>
		<truncated>0</truncated>
		<difficult>0</difficult>
		<bndbox>
			<xmin>4</xmin>
			<ymin>620</ymin>
			<xmax>168</xmax>
			<ymax>752</ymax>
		</bndbox>
	</object>
	<object>
		<name>bus</name>
		<pose>Unspecified</pose>
		<truncated>0</truncated>
		<difficult>0</difficult>
		<bndbox>
			<xmin>606</xmin>
			<ymin>392</ymin>
			<xmax>1022</xmax>
			<ymax>878</ymax>
		</bndbox>
	</object>
	<object>
		<name>person</name>
		<pose>Unspecified</pose>
		<truncated>0</truncated>
		<difficult>0</difficult>
		<bndbox>
			<xmin>1241</xmin>
			<ymin>641</ymin>
			<xmax>1253</xmax>
			<ymax>667</ymax>
		</bndbox>
	</object>
</annotation>
